openvcad.libs/libbz2-a1e77c99.so.1.0.6
openvcad.libs/libfontconfig-dcb2ce6c.so.1.12.0
openvcad.libs/libfreetype-2f3b32b6.so.6.16.1
openvcad.libs/libpng16-748299c7.so.16.34.0
openvcad.libs/libuuid-e4c4d8e4.so.1.3.0
pyvcad/__init__.py
pyvcad/pyvcad.cpython-313-x86_64-linux-gnu.so
pyvcad/configs/default.json
pyvcad/configs/j750.json
pyvcad_compilers/__init__.py
pyvcad_compilers/pyvcad_compilers.cpython-313-x86_64-linux-gnu.so
openvcad-2.3.3.dist-info/METADATA
openvcad-2.3.3.dist-info/WHEEL
openvcad-2.3.3.dist-info/RECORD
openvcad-2.3.3.dist-info/licenses/LICENSE
openvcad-2.3.3.dist-info/sboms/auditwheel.cdx.json
