Metadata-Version: 2.2
Name: OpenVCAD
Version: 2.3.3
Summary: Python bindings for OpenVCAD (pyvcad, pyvcad_compilers, pyvcad_rendering)
Keywords: 3D printing,CAD,multi-material,volumetric,CSG,geometry,3D,functionaly graded materials
Author-Email: Charles Wade <charles.wade@colorado.edu>, Robert MacCurdy <maccurdy@colorado.edu>
License: Copyright © 2025 The Regents of the University of Colorado, a body corporate.
Project-URL: Homepage, https://matterassembly.org/openvcad
Project-URL: Documentation, https://matterassembly.org/openvcad-developer-dev/
Requires-Python: >=3.11
Requires-Dist: pyvcad-rendering>=1.0.3
